CHANGES
LICENSE
README
TODO
setup.cfg
setup.py
BrightContent.egg-info/PKG-INFO
BrightContent.egg-info/SOURCES.txt
BrightContent.egg-info/dependency_links.txt
BrightContent.egg-info/entry_points.txt
BrightContent.egg-info/not-zip-safe
BrightContent.egg-info/requires.txt
BrightContent.egg-info/top_level.txt
brightcontent/__init__.py
brightcontent/highlightpythoncode.py
brightcontent/util.py
brightcontent/wsgiapp.py
brightcontent/core/__init__.py
brightcontent/core/app.py
brightcontent/core/renderer.py
brightcontent/core/store.py
brightcontent/static/atom-rdfa.xslt
brightcontent/static/util.xslt
brightcontent/static/bluesky/LICENSE.txt
brightcontent/static/bluesky/index.xslt
brightcontent/static/bluesky/readme.txt
brightcontent/static/bluesky/css/bluesky.css
brightcontent/static/bluesky/css/bluesky_alt_bright.css
brightcontent/static/bluesky/css/bluesky_alt_handheld.css
brightcontent/static/bluesky/css/bluesky_alt_large.css
brightcontent/static/bluesky/css/bluesky_alt_no_borders.css
brightcontent/static/bluesky/css/bluesky_alt_plain.css
brightcontent/static/bluesky/css/bluesky_alt_right_nav.css
brightcontent/static/bluesky/css/print.css
brightcontent/static/bluesky/images/alt3_main_bg.png
brightcontent/static/bluesky/images/background.png
brightcontent/static/bluesky/images/img1.jpg
brightcontent/static/bluesky/images/img2.jpg
brightcontent/static/contented6/index.xslt
brightcontent/static/contented6/css/style.css
brightcontent/static/naturalist/index.xslt
brightcontent/static/naturalist/css/style.css
brightcontent/static/naturalist/images/bg.jpg
brightcontent/static/naturalist/images/content_bg.jpg
brightcontent/static/naturalist/images/footer.jpg
brightcontent/static/naturalist/images/header.jpg
brightcontent/static/naturalist/images/menu_bg.jpg
brightcontent/static/naturalist/images/page_bg.jpg
brightcontent/static/two-tenths/index.xslt
brightcontent/static/two-tenths/css/screen.css
docs/devel_config.ini
etc/import-feed.py
tests/conftest.py
tests/test_app.py
