Metadata-Version: 1.0
Name: BrightContent
Version: 0.1
Summary: Bright Content is Python Weblog software built from reusable components.
Home-page: http://brightcontent.net
Author: Uche Ogbuji and Julian Krause
Author-email: brightcontent@brightcontent.net
License: AFL
Keywords: wsgi atom blog
Platform: UNKNOWN
Classifier: Development Status :: 3 - Alpha
Classifier: Environment :: Web Environment
Classifier: License :: OSI Approved :: Academic Free License (AFL)
Classifier: Topic :: Internet :: WWW/HTTP :: Dynamic Content :: News/Diary
Classifier: Topic :: Text Processing :: Markup :: XML
Classifier: Topic :: Internet :: WWW/HTTP :: WSGI :: Application
Classifier: Topic :: Internet :: WWW/HTTP :: WSGI :: Middleware
